{
  "timestamp": "2025-12-20T21:37:37.861536",
  "ticker": "XRP-USD",
  "data_points": 3732,
  "latest_signal": {
    "date": "2025-12-19",
    "signal": "HOLD",
    "position": "LONG",
    "phase_quadrant": "Quadrante 1 (Minimo -> Salita)",
    "phase_value": -2.1880788767428934,
    "oscillator_value": -0.16118710953250037,
    "signal_strength": 15.999781054225389,
    "confidence": "LOW",
    "price": 1.9073921922,
    "timestamp": "2025-12-20T21:37:36.405733"
  },
  "backtest_metrics": {
    "total_return_%": 527.9746124210054,
    "max_drawdown_%": 3.863790018377166,
    "sharpe_ratio": 0.7188165580374574,
    "sortino_ratio": 2.3517431928741903,
    "calmar_ratio": 15.243089426616795,
    "total_trades": 14,
    "win_rate_%": 71.42857142857143,
    "profit_factor": 25.770304489111485
  },
  "cycle_analysis": {
    "dominant_period": 126.0,
    "p_value": 0.0,
    "significant": "True"
  }
}